odoo/addons/sale_automatic_workflow_payment/README.rst
odoo/addons/sale_automatic_workflow_payment/__init__.py
odoo/addons/sale_automatic_workflow_payment/__manifest__.py
odoo/addons/sale_automatic_workflow_payment/i18n/es.po
odoo/addons/sale_automatic_workflow_payment/i18n/sale_automatic_workflow_payment.pot
odoo/addons/sale_automatic_workflow_payment/models/__init__.py
odoo/addons/sale_automatic_workflow_payment/models/payment_acquirer.py
odoo/addons/sale_automatic_workflow_payment/models/payment_transaction.py
odoo/addons/sale_automatic_workflow_payment/readme/CONTRIBUTORS.rst
odoo/addons/sale_automatic_workflow_payment/readme/DESCRIPTION.rst
odoo/addons/sale_automatic_workflow_payment/readme/USAGE.rst
odoo/addons/sale_automatic_workflow_payment/static/description/icon.png
odoo/addons/sale_automatic_workflow_payment/static/description/index.html
odoo/addons/sale_automatic_workflow_payment/tests/__init__.py
odoo/addons/sale_automatic_workflow_payment/tests/test_automatic_payment.py
odoo/addons/sale_automatic_workflow_payment/views/payment_acquirer.xml
odoo13_addon_sale_automatic_workflow_payment-13.0.1.0.1.dev6.dist-info/METADATA
odoo13_addon_sale_automatic_workflow_payment-13.0.1.0.1.dev6.dist-info/WHEEL
odoo13_addon_sale_automatic_workflow_payment-13.0.1.0.1.dev6.dist-info/top_level.txt
odoo13_addon_sale_automatic_workflow_payment-13.0.1.0.1.dev6.dist-info/RECORD
