Metadata-Version: 2.1
Name: odoo13-addon-sale-automatic-workflow-payment
Version: 13.0.1.0.1.dev6
Summary: Assign a workflow if a transaction is created for a sale order with an acquirer with a workflow
Home-page: https://github.com/OCA/sale-workflow
Author: ACSONE SA/NV,Odoo Community Association (OCA)
Author-email: support@odoo-community.org
License: AGPL-3
Platform: UNKNOWN
Classifier: Programming Language :: Python
Classifier: Framework :: Odoo
Classifier: Framework :: Odoo :: 13.0
Classifier: License :: OSI Approved :: GNU Affero General Public License v3
Classifier: Development Status :: 4 - Beta
Requires-Python: >=3.5
Requires-Dist: odoo13-addon-sale-automatic-workflow
Requires-Dist: odoo <13.1dev,>=13.0a
